.gitignore
CHANGELOG.md
LICENSE
MANIFEST.in
README.md
requirements.txt
setup.cfg
setup.py
pltstat/__init__.py
pltstat/circle.py
pltstat/cm.py
pltstat/in_out.py
pltstat/multfeats.py
pltstat/singlefeat.py
pltstat/stat_methods.py
pltstat/tests.py
pltstat/twofeats.py
pltstat.egg-info/PKG-INFO
pltstat.egg-info/SOURCES.txt
pltstat.egg-info/dependency_links.txt
pltstat.egg-info/requires.txt
pltstat.egg-info/top_level.txt