Metadata-Version: 2.1
Name: pltstat
Version: 0.10.0
Summary: A Python Library for Statistical Data Visualization
Home-page: https://github.com/trojanskehesten/pltstat
Download-URL: https://github.com/trojanskehesten/pltstat/archive/refs/tags/v0.10.0.zip
Author: Dmitrii Beregovoi
Author-email: dimaforth@gmail.com
License: BSD 3-Clause License, see LICENSE file
Keywords: matplotlib,statistics,visualization,dataanalysis
Classifier: Development Status :: 4 - Beta
Classifier: Intended Audience :: Science/Research
Classifier: Intended Audience :: Developers
Classifier: License :: OSI Approved :: BSD License
Classifier: Programming Language :: Python :: 3.12
Classifier: Programming Language :: Python :: 3
Classifier: Operating System :: OS Independent
Classifier: Topic :: Scientific/Engineering :: Visualization
Classifier: Topic :: Scientific/Engineering :: Mathematics
Classifier: Topic :: Software Development :: Libraries :: Python Modules
Classifier: Natural Language :: English
Requires-Python: ~=3.12
License-File: LICENSE
Requires-Dist: numpy~=2.0.2
Requires-Dist: pandas~=2.2.3
Requires-Dist: matplotlib~=3.10.0
Requires-Dist: seaborn~=0.13.2
Requires-Dist: umap-learn~=0.5.7
Requires-Dist: scipy~=1.15.2
Requires-Dist: scikit-learn~=1.6.0
Requires-Dist: phik~=0.12.4
